ecoaliface/__init__.py
ecoaliface/simple.py
examples/__init__.py
examples/async_use.py
examples/ecoaliface/__init__.py
examples/ecoaliface/simple.py
ecoaliface-0.7.0.dist-info/LICENSE
ecoaliface-0.7.0.dist-info/METADATA
ecoaliface-0.7.0.dist-info/WHEEL
ecoaliface-0.7.0.dist-info/top_level.txt
ecoaliface-0.7.0.dist-info/RECORD
