Metadata-Version: 2.1
Name: ecoaliface
Version: 0.7.0
Summary: Interface to eSterownik.pl eCoal water boiler controller.
Home-page: https://github.com/matkor/ecoaliface
Author: Mateusz Korniak
Author-email: matkorpypiorg@ant.gliwice.pl
License: GPLv3+
Classifier: Programming Language :: Python :: 3
Classifier: License :: OSI Approved :: GNU General Public License v3 or later (GPLv3+)
Classifier: Operating System :: OS Independent
Classifier: Development Status :: 4 - Beta
License-File: LICENSE
Requires-Dist: requests
